saigon_test/.flake8
saigon_test/__init__.py
saigon_test/fixtures.py
saigon_test/infra.py
saigon_test/lint.py
saigon_test/cli/__init__.py
saigon_test/cli/cognito.py
saigon_test/cli/shell/__init__.py
saigon_test/cli/shell/handlers.py
saigon_test/cli/shell/shell.py
saigon_py_test-0.11.8.dist-info/METADATA
saigon_py_test-0.11.8.dist-info/WHEEL
saigon_py_test-0.11.8.dist-info/entry_points.txt
saigon_py_test-0.11.8.dist-info/RECORD
