Metadata-Version: 2.4
Name: saigon-py-test
Version: 0.11.8
Summary: Common components to build digital backends
Project-URL: Source Code, https://github.com/abastidian/saigon
Author: abastidian@gmail.com
Classifier: Programming Language :: Python :: 3
Requires-Python: >=3.13
Requires-Dist: psycopg~=3.2.9
Requires-Dist: saigon-py[aws,backend,dev]==0.11.8
